NeighborBlend.py
NeighborBlend-0.3.0.dist-info/LICENSE.txt
NeighborBlend-0.3.0.dist-info/METADATA
NeighborBlend-0.3.0.dist-info/WHEEL
NeighborBlend-0.3.0.dist-info/top_level.txt
NeighborBlend-0.3.0.dist-info/RECORD
