Metadata-Version: 2.1
Name: NeighborBlend
Version: 0.3.0
Summary: UNKNOWN
Home-page: https://github.com/sonisanskar/Neighborhood-Blending
Author: Soni Sanskar
Author-email: soni.sanskar@gmail.com
License: MIT
Platform: UNKNOWN
Classifier: Programming Language :: Python :: 3.5
Classifier: Programming Language :: Python :: 3.7
Classifier: Programming Language :: Python :: 3.8
Classifier: Topic :: Scientific/Engineering :: Artificial Intelligence
Classifier: License :: OSI Approved :: MIT License
Classifier: Operating System :: OS Independent
Requires-Python: >=3
Requires-Dist: numpy
Requires-Dist: pandas
Requires-Dist: faiss-cpu
Requires-Dist: scikit-learn
